btcquant/__init__.py
btcquant/config.py
btcquant/exchange.py
btcquant-2.0.3.dist-info/METADATA
btcquant-2.0.3.dist-info/RECORD
btcquant-2.0.3.dist-info/WHEEL
btcquant-2.0.3.dist-info/top_level.txt
btcquant-2.0.3.dist-info/zip-safe
